horizon_tc_ui/__init__.py
horizon_tc_ui/hb_bin_maker.py
horizon_tc_ui/hb_binruntime.py
horizon_tc_ui/hb_checker.py
horizon_tc_ui/hb_custom_op.py
horizon_tc_ui/hb_eval_preprocess.py
horizon_tc_ui/hb_extract_hbm.py
horizon_tc_ui/hb_mapper.py
horizon_tc_ui/hb_mapper_checker.py
horizon_tc_ui/hb_mapper_infer.py
horizon_tc_ui/hb_mapper_makertbin.py
horizon_tc_ui/hb_model_info.py
horizon_tc_ui/hb_model_modifier.py
horizon_tc_ui/hb_onnx_info.py
horizon_tc_ui/hb_onnxruntime.py
horizon_tc_ui/hb_pack.py
horizon_tc_ui/hb_perf.py
horizon_tc_ui/hb_verifier.py
horizon_tc_ui/helper.py
horizon_tc_ui/vec_diff.py
horizon_tc_ui/version.py
horizon_tc_ui/config/__init__.py
horizon_tc_ui/config/config_info.py
horizon_tc_ui/config/fast_perf_template.yaml
horizon_tc_ui/config/mapper_conf_parser.py
horizon_tc_ui/config/mapper_consts.py
horizon_tc_ui/custom_op_template/__init__.py
horizon_tc_ui/custom_op_template/sample_custom.py
horizon_tc_ui/data/__init__.py
horizon_tc_ui/data/cifar_val.py
horizon_tc_ui/data/coco_val.py
horizon_tc_ui/data/data_loader_factory.py
horizon_tc_ui/data/dataloader.py
horizon_tc_ui/data/dataset.py
horizon_tc_ui/data/dataset_consts.py
horizon_tc_ui/data/dataset_loader.py
horizon_tc_ui/data/imagenet_val.py
horizon_tc_ui/data/imfiletorgb.py
horizon_tc_ui/data/loader.py
horizon_tc_ui/data/raw_data_reader.py
horizon_tc_ui/data/transformer.py
horizon_tc_ui/data/voc_val_piece.py
horizon_tc_ui/eval_preprocess/__init__.py
horizon_tc_ui/eval_preprocess/conf.py
horizon_tc_ui/eval_preprocess/data_transformer.py
horizon_tc_ui/eval_preprocess/dataloader.py
horizon_tc_ui/eval_preprocess/eval_preprocess.py
horizon_tc_ui/hbdtort/__init__.py
horizon_tc_ui/hbdtort/graph_tool.py
horizon_tc_ui/hbdtort/layout_util.py
horizon_tc_ui/hbdtort/model_package_pb2.py
horizon_tc_ui/hbdtort/onnx2horizonrt.py
horizon_tc_ui/hbdtort/onnx_debug.py
horizon_tc_ui/hbdtort/onnx_layout_util.py
horizon_tc_ui/hbdtort/operator_fusion.py
horizon_tc_ui/hbdtort/report_gen.py
rdkx5_yolo_mapper-1.0.0.dist-info/METADATA
rdkx5_yolo_mapper-1.0.0.dist-info/WHEEL
rdkx5_yolo_mapper-1.0.0.dist-info/entry_points.txt
rdkx5_yolo_mapper-1.0.0.dist-info/top_level.txt
rdkx5_yolo_mapper-1.0.0.dist-info/RECORD
