Metadata-Version: 2.1
Name: rdkx5_yolo_mapper
Version: 1.0.0
Summary: D-Robotics Algorithm Toolchain User Interface
Home-page: https://developer-d-robotics.cc
Author: D-Robotics
Keywords: D-Robotics Algorithm Toolchain User Interface
Requires-Python: ~=3.10
Requires-Dist: dgdk
Requires-Dist: dg_nn_toolkit
Requires-Dist: click >=7.1.2
Requires-Dist: pyyaml >=5.3.1
Requires-Dist: schema >=0.7.2
Requires-Dist: easydict >=1.7
Requires-Dist: pathos >=0.2.4
Requires-Dist: absl-py >=1.3.0
Requires-Dist: graphviz >=0.8.4
Requires-Dist: jinja2 >=3.0.3
Requires-Dist: tqdm >=4.64.1
Requires-Dist: protobuf ==3.20.3
Requires-Dist: paramiko >=2.12.0
Requires-Dist: opencv-python ==4.6.0.66
Requires-Dist: pycocotools
Requires-Dist: onnx ==1.15.0
Requires-Dist: psutil
Requires-Dist: numpy ==1.23.0
Requires-Dist: scikit-image ==0.19.0
Requires-Dist: onnxruntime ==1.16.2
